multiversx_sdk_wallet/__init__.py
multiversx_sdk_wallet/constants.py
multiversx_sdk_wallet/core.py
multiversx_sdk_wallet/errors.py
multiversx_sdk_wallet/interfaces.py
multiversx_sdk_wallet/mnemonic.py
multiversx_sdk_wallet/mnemonic_test.py
multiversx_sdk_wallet/pem_entry.py
multiversx_sdk_wallet/pem_entry_test.py
multiversx_sdk_wallet/py.typed
multiversx_sdk_wallet/user_keys.py
multiversx_sdk_wallet/user_pem.py
multiversx_sdk_wallet/user_signer.py
multiversx_sdk_wallet/user_test.py
multiversx_sdk_wallet/user_verifer.py
multiversx_sdk_wallet/user_wallet.py
multiversx_sdk_wallet/validator_keys.py
multiversx_sdk_wallet/validator_pem.py
multiversx_sdk_wallet/validator_signer.py
multiversx_sdk_wallet/validator_test.py
multiversx_sdk_wallet/validator_verifier.py
multiversx_sdk_wallet/crypto/__init__.py
multiversx_sdk_wallet/crypto/constants.py
multiversx_sdk_wallet/crypto/decryptor.py
multiversx_sdk_wallet/crypto/encrypted_data.py
multiversx_sdk_wallet/crypto/encryptor.py
multiversx_sdk_wallet/crypto/randomness.py
multiversx_sdk_wallet/libraries/__init__.py
multiversx_sdk_wallet/libraries/bls_facade.py
multiversx_sdk_wallet/libraries/bls_facade_test.py
multiversx_sdk_wallet/libraries/libbls.dll
multiversx_sdk_wallet/libraries/libbls.dylib
multiversx_sdk_wallet/libraries/libbls.so
multiversx_sdk_wallet/libraries/libbls_arm64.dylib
multiversx_sdk_wallet-0.9.3.dist-info/METADATA
multiversx_sdk_wallet-0.9.3.dist-info/WHEEL
multiversx_sdk_wallet-0.9.3.dist-info/licenses/LICENSE
multiversx_sdk_wallet-0.9.3.dist-info/RECORD
