Metadata-Version: 2.3
Name: multiversx-sdk-wallet
Version: 0.9.3
Summary: Wallet & crypto components of MultiversX Python SDK.
Project-URL: Homepage, https://github.com/multiversx/mx-sdk-py-wallet
Author: MultiversX
License-Expression: MIT
License-File: LICENSE
Classifier: License :: OSI Approved :: MIT License
Classifier: Operating System :: OS Independent
Classifier: Programming Language :: Python :: 3
Requires-Python: >=3.8
Requires-Dist: cryptography==42.0.4
Requires-Dist: mnemonic==0.20
Requires-Dist: multiversx-sdk-core<0.9.0,>=0.8.0
Requires-Dist: pynacl==1.5.0
